[{"py/object": "textrazor.Entity", "_matched_words": [], "json": {"confidenceScore": 0.9592, "endingPos": 2742, "entityEnglishId": "Educational game", "entityId": "Educational game", "freebaseId": "/m/01sjp9", "freebaseTypes": ["/cvg/cvg_genre", "/media_common/media_genre", "/book/book_subject"], "id": 46, "matchedText": "educational games", "matchingTokens": [553, 554], "relevanceScore": 0.7399, "startingPos": 2725, "wikiLink": "http://en.wikipedia.org/wiki/Educational_game", "wikidataId": "Q1140363"}}, {"py/object": "textrazor.Entity", "_matched_words": [], "json": {"confidenceScore": 3.406, "endingPos": 2937, "entityEnglishId": "Education", "entityId": "Education", "freebaseId": "/m/02jfc", "freebaseTypes": ["/business/customer", "/film/film_genre", "/games/game_genre", "/tv/tv_genre", "/organization/organization_sector", "/architecture/building_complex_function", "/media_common/media_genre", "/book/book_subject", "/people/professional_field", "/government/government_service", "/media_common/quotation_subject", "/organization/contact_category", "/book/periodical_subject", "/business/competitive_space", "/cvg/cvg_genre", "/business/brand", "/conferences/conference_subject", "/media_common/literary_genre", "/broadcast/genre", "/award/award_discipline", "/internet/website_category", "/education/field_of_study", "/atom/feed_category", "/business/industry", "/organization/organization_type", "/film/film_subject"], "id": 26, "matchedText": "education", "matchingTokens": [592], "relevanceScore": 0.6606, "startingPos": 2928, "wikiLink": "http://en.wikipedia.org/wiki/Education", "wikidataId": "Q8434"}}, {"py/object": "textrazor.Entity", "_matched_words": [], "json": {"confidenceScore": 4.657, "endingPos": 2613, "entityEnglishId": "Curriculum", "entityId": "Curriculum", "freebaseId": "/m/02fk8v", "freebaseTypes": ["/book/book_subject", "/education/field_of_study"], "id": 33, "matchedText": "curriculum", "matchingTokens": [530], "relevanceScore": 0.637, "startingPos": 2603, "wikiLink": "http://en.wikipedia.org/wiki/Curriculum", "wikidataId": "Q207137"}}, {"py/object": "textrazor.Entity", "_matched_words": [], "json": {"confidenceScore": 1.319, "endingPos": 1571, "entityEnglishId": "Teacher", "entityId": "Teacher", "freebaseId": "/m/093fw9", "freebaseTypes": ["/people/profession", "/book/book_subject", "/organization/contact_category", "/fictional_universe/character_occupation", "/people/profession"], "id": 25, "matchedText": "teaching", "matchingTokens": [314], "relevanceScore": 0.616, "startingPos": 1563, "wikiLink": "http://en.wikipedia.org/wiki/Teacher", "wikidataId": "Q37226"}}, {"py/object": "textrazor.Entity", "_matched_words": [], "json": {"confidenceScore": 2.962, "endingPos": 507, "entityEnglishId": "Classroom", "entityId": "Classroom", "freebaseId": "/m/04hyxm", "freebaseTypes": ["/architecture/building_function"], "id": 34, "matchedText": "classroom", "matchingTokens": [94], "relevanceScore": 0.5765, "startingPos": 498, "wikiLink": "http://en.wikipedia.org/wiki/Classroom", "wikidataId": "Q621114"}}, {"py/object": "textrazor.Entity", "_matched_words": [], "json": {"confidenceScore": 2.631, "endingPos": 4626, "entityEnglishId": "Lesson plan", "entityId": "Lesson plan", "freebaseId": "/m/08hfyd", "id": 49, "matchedText": "lesson plan", "matchingTokens": [923, 924], "relevanceScore": 0.5755, "startingPos": 4615, "wikiLink": "http://en.wikipedia.org/wiki/Lesson_plan", "wikidataId": "Q2033770"}}, {"py/object": "textrazor.Entity", "_matched_words": [], "json": {"confidenceScore": 3.813, "endingPos": 4272, "entityEnglishId": "Website", "entityId": "Website", "freebaseId": "/m/027r4xw", "freebaseTypes": ["/book/book_subject", "/business/industry", "/award/award_category", "/dataworld/information_source", "/fictional_universe/fictional_organization_type", "/organization/non_profit_organization", "/location/location", "/internet/website_category", "/award/award_discipline", "/organization/contact_category", "/business/business_location", "/education/school_category", "/organization/role", "/business/employer", "/organization/organization_sector", "/organization/organization", "/business/industry", "/dataworld/information_source", "/internet/website_category"], "id": 28, "matchedText": "website", "matchingTokens": [851], "relevanceScore": 0.5563, "startingPos": 4265, "wikiLink": "http://en.wikipedia.org/wiki/Website", "wikidataId": "Q35127"}}, {"py/object": "textrazor.Entity", "_matched_words": [], "json": {"confidenceScore": 11.1, "endingPos": 3259, "entityEnglishId": "Mathematics", "entityId": "Mathematics", "freebaseId": "/m/04rjg", "freebaseTypes": ["/education/field_of_study", "/book/periodical_subject", "/book/book_subject", "/computer/programming_language_paradigm", "/media_common/quotation_subject", "/award/award_discipline", "/film/film_subject", "/interests/hobby", "/award/competition_type", "/education/school_category", "/computer/software_genre", "/exhibitions/exhibition_subject", "/media_common/literary_genre", "/internet/website_category", "/interests/interest", "/media_common/netflix_genre", "/organization/organization_sector", "/media_common/media_genre", "/conferences/conference_subject"], "id": 69, "matchedText": "math", "matchingTokens": [654], "relevanceScore": 0.5184, "startingPos": 3255, "wikiLink": "http://en.wikipedia.org/wiki/Mathematics", "wikidataId": "Q395"}}, {"py/object": "textrazor.Entity", "_matched_words": [], "json": {"confidenceScore": 10.68, "endingPos": 1382, "entityEnglishId": "Video game", "entityId": "Video game", "freebaseId": "/m/01mw1", "freebaseTypes": ["/business/industry", "/film/film_subject", "/award/award_discipline", "/award/competition_type", "/exhibitions/exhibition_subject", "/business/product_category", "/computer/software_genre", "/interests/hobby", "/comic_strips/comic_strip_genre", "/internet/website_category", "/media_common/media_genre", "/organization/organization_sector", "/interests/interest", "/broadcast/genre", "/book/book_subject", "/interests/collection_category", "/tv/tv_genre", "/book/periodical_subject"], "id": 75, "matchedText": "video games", "matchingTokens": [274, 275], "relevanceScore": 0.4696, "startingPos": 1371, "wikiLink": "http://en.wikipedia.org/wiki/Video_game", "wikidataId": "Q7889"}}, {"py/object": "textrazor.Entity", "_matched_words": [], "json": {"confidenceScore": 1.523, "endingPos": 1922, "entityEnglishId": "World Wide Web", "entityId": "World Wide Web", "freebaseId": "/m/0828v", "freebaseTypes": ["/law/invention", "/location/location", "/visual_art/visual_art_medium", "/computer/protocol_provider", "/organization/organization_sector", "/periodicals/newspaper_circulation_area", "/dataworld/information_source", "/cvg/cvg_platform"], "id": 54, "matchedText": "web", "matchingTokens": [391], "relevanceScore": 0.458, "startingPos": 1919, "wikiLink": "http://en.wikipedia.org/wiki/World_Wide_Web", "wikidataId": "Q466"}}, {"py/object": "textrazor.Entity", "_matched_words": [], "json": {"confidenceScore": 5.058, "endingPos": 1420, "entityEnglishId": "Learning", "entityId": "Learning", "freebaseId": "/m/0191f8", "freebaseTypes": ["/interests/hobby", "/interests/interest", "/media_common/quotation_subject", "/projects/project_focus", "/education/field_of_study"], "id": 24, "matchedText": "learning", "matchingTokens": [282], "relevanceScore": 0.4528, "startingPos": 1412, "wikiLink": "http://en.wikipedia.org/wiki/Learning", "wikidataId": "Q133500"}}, {"py/object": "textrazor.Entity", "_matched_words": [], "json": {"confidenceScore": 4.899, "endingPos": 167, "entityEnglishId": "Research", "entityId": "Research", "freebaseId": "/m/06cs1", "freebaseTypes": ["/architecture/building_function", "/education/school_category", "/book/periodical_subject", "/spaceflight/satellite_type", "/media_common/quotation_subject", "/book/book_subject", "/business/industry", "/organization/organization_sector", "/architecture/building_complex_function", "/organization/organization_type", "/education/field_of_study", "/award/award_discipline"], "id": 86, "matchedText": "research", "matchingTokens": [30], "relevanceScore": 0.4489, "startingPos": 159, "wikiLink": "http://en.wikipedia.org/wiki/Research", "wikidataId": "Q42240"}}, {"py/object": "textrazor.Entity", "_matched_words": [], "json": {"confidenceScore": 11.21, "endingPos": 3271, "entityEnglishId": "Science", "entityId": "Science", "freebaseId": "/m/06mq7", "freebaseTypes": ["/award/award_discipline", "/radio/radio_subject", "/book/periodical_subject", "/media_common/quotation_subject", "/internet/website_category", "/education/field_of_study", "/theater/theater_genre", "/organization/organization_sector", "/book/book_subject", "/media_common/literary_genre", "/film/film_genre", "/media_common/netflix_genre", "/film/film_subject", "/broadcast/genre", "/tv/tv_subject", "/tv/tv_genre", "/media_common/media_genre"], "id": 70, "matchedText": "science", "matchingTokens": [656], "relevanceScore": 0.4445, "startingPos": 3264, "wikiLink": "http://en.wikipedia.org/wiki/Science", "wikidataId": "Q336"}}, {"py/object": "textrazor.Entity", "_matched_words": [], "json": {"confidenceScore": 0.9689, "endingPos": 1199, "entityEnglishId": "Library", "entityId": "Library", "freebaseId": "/m/04h8h", "freebaseTypes": ["/location/location", "/internet/website_category", "/book/book_subject", "/architecture/building_function", "/business/industry", "/organization/organization_sector", "/computer/software_genre", "/media_common/quotation_subject", "/organization/contact_category"], "id": 85, "matchedText": "library", "matchingTokens": [236], "relevanceScore": 0.4347, "startingPos": 1192, "wikiLink": "http://en.wikipedia.org/wiki/Library", "wikidataId": "Q7075"}}, {"py/object": "textrazor.Entity", "_matched_words": [], "json": {"confidenceScore": 12.02, "endingPos": 2077, "entityEnglishId": "Computer", "entityId": "Computer", "freebaseId": "/m/01m3v", "freebaseTypes": ["/music/instrument", "/music/performance_role", "/education/field_of_study", "/organization/organization_sector", "/media_common/quotation_subject", "/award/award_discipline", "/business/industry", "/book/book_subject", "/fictional_universe/character_species", "/education/school_category"], "id": 81, "matchedText": "computer", "matchingTokens": [422], "relevanceScore": 0.4203, "startingPos": 2069, "wikiLink": "http://en.wikipedia.org/wiki/Computer", "wikidataId": "Q68"}}]