[{"py/object": "textrazor.Entity", "_matched_words": [], "json": {"confidenceScore": 1.747, "endingPos": 4818, "entityEnglishId": "Learning styles", "entityId": "Learning styles", "freebaseId": "/m/03yk2w", "id": 63, "matchedText": "learning style", "matchingTokens": [823, 824], "relevanceScore": 1, "startingPos": 4804, "wikiLink": "http://en.wikipedia.org/wiki/Learning_styles", "wikidataId": "Q1820370"}}, {"py/object": "textrazor.Entity", "_matched_words": [], "json": {"confidenceScore": 9.664, "endingPos": 2187, "entityEnglishId": "Educational technology", "entityId": "Educational technology", "freebaseId": "/m/03c4pp0", "freebaseTypes": ["/education/field_of_study", "/people/profession"], "id": 14, "matchedText": "e-learning", "matchingTokens": [371], "relevanceScore": 0.9641, "startingPos": 2177, "wikiLink": "http://en.wikipedia.org/wiki/Educational_technology", "wikidataId": "Q1068473"}}, {"py/object": "textrazor.Entity", "_matched_words": [], "json": {"confidenceScore": 11, "endingPos": 3314, "entityEnglishId": "Massive open online course", "entityId": "Massive open online course", "freebaseId": "/m/0gyvy46", "freebaseTypes": ["/internet/website_category"], "id": 38, "matchedText": "MOOCs", "matchingTokens": [570], "relevanceScore": 0.9061, "startingPos": 3309, "wikiLink": "http://en.wikipedia.org/wiki/Massive_open_online_course", "wikidataId": "Q967853"}}, {"py/object": "textrazor.Entity", "_matched_words": [], "json": {"confidenceScore": 1.427, "endingPos": 5264, "entityEnglishId": "Reading comprehension", "entityId": "Reading comprehension", "freebaseId": "/m/05js3c", "id": 13, "matchedText": "comprehension", "matchingTokens": [897], "relevanceScore": 0.8982, "startingPos": 5251, "wikiLink": "http://en.wikipedia.org/wiki/Reading_comprehension", "wikidataId": "Q3269423"}}, {"py/object": "textrazor.Entity", "_matched_words": [], "json": {"confidenceScore": 8.268, "endingPos": 4475, "entityEnglishId": "Learning", "entityId": "Learning", "freebaseId": "/m/0191f8", "freebaseTypes": ["/interests/hobby", "/interests/interest", "/media_common/quotation_subject", "/projects/project_focus", "/education/field_of_study"], "id": 268, "matchedText": "learni", "matchingTokens": [761], "relevanceScore": 0.896, "startingPos": 4469, "wikiLink": "http://en.wikipedia.org/wiki/Learning", "wikidataId": "Q133500"}}, {"py/object": "textrazor.Entity", "_matched_words": [], "json": {"confidenceScore": 5.236, "endingPos": 1546, "entityEnglishId": "Distance education", "entityId": "Distance education", "freebaseId": "/m/06zscb_", "freebaseTypes": ["/organization/organization", "/organization/organization_sector", "/location/location", "/education/educational_institution_campus", "/business/employer", "/education/school_category"], "id": 266, "matchedText": "Distance Education", "matchingTokens": [267, 268], "relevanceScore": 0.8552, "startingPos": 1528, "wikiLink": "http://en.wikipedia.org/wiki/Distance_education", "wikidataId": "Q159595"}}, {"py/object": "textrazor.Entity", "_matched_words": [], "json": {"confidenceScore": 0.9903, "endingPos": 3929, "entityEnglishId": "Educational assessment", "entityId": "Educational assessment", "freebaseId": "/m/02csbb", "freebaseTypes": ["/computer/software_genre", "/business/product_category", "/education/field_of_study"], "id": 231, "matchedText": "assessment", "matchingTokens": [672], "relevanceScore": 0.7935, "startingPos": 3919, "wikiLink": "http://en.wikipedia.org/wiki/Educational_assessment", "wikidataId": "Q2585724"}}, {"py/object": "textrazor.Entity", "_matched_words": [], "json": {"confidenceScore": 4.54, "endingPos": 1546, "entityEnglishId": "Education", "entityId": "Education", "freebaseId": "/m/02jfc", "freebaseTypes": ["/business/customer", "/film/film_genre", "/games/game_genre", "/tv/tv_genre", "/organization/organization_sector", "/architecture/building_complex_function", "/media_common/media_genre", "/book/book_subject", "/people/professional_field", "/government/government_service", "/media_common/quotation_subject", "/organization/contact_category", "/book/periodical_subject", "/business/competitive_space", "/cvg/cvg_genre", "/business/brand", "/conferences/conference_subject", "/media_common/literary_genre", "/broadcast/genre", "/award/award_discipline", "/internet/website_category", "/education/field_of_study", "/atom/feed_category", "/business/industry", "/organization/organization_type", "/film/film_subject"], "id": 265, "matchedText": "Education", "matchingTokens": [268], "relevanceScore": 0.7798, "startingPos": 1537, "wikiLink": "http://en.wikipedia.org/wiki/Education", "wikidataId": "Q8434"}}, {"py/object": "textrazor.Entity", "_matched_words": [], "json": {"confidenceScore": 1.874, "endingPos": 684, "entityEnglishId": "Personalized learning", "entityId": "Personalized learning", "freebaseId": "/m/0dln43p", "id": 153, "matchedText": "personalized learning", "matchingTokens": [118, 119], "relevanceScore": 0.7383, "startingPos": 663, "wikiLink": "http://en.wikipedia.org/wiki/Personalized_learning", "wikidataId": "Q3620943"}}, {"py/object": "textrazor.Entity", "_matched_words": [], "json": {"confidenceScore": 8.563, "endingPos": 4430, "entityEnglishId": "Research", "entityId": "Research", "freebaseId": "/m/06cs1", "freebaseTypes": ["/architecture/building_function", "/education/school_category", "/book/periodical_subject", "/spaceflight/satellite_type", "/media_common/quotation_subject", "/book/book_subject", "/business/industry", "/organization/organization_sector", "/architecture/building_complex_function", "/organization/organization_type", "/education/field_of_study", "/award/award_discipline"], "id": 256, "matchedText": "researchers", "matchingTokens": [755], "relevanceScore": 0.7331, "startingPos": 4419, "wikiLink": "http://en.wikipedia.org/wiki/Research", "wikidataId": "Q42240"}}, {"py/object": "textrazor.Entity", "_matched_words": [], "json": {"confidenceScore": 5.216, "endingPos": 4219, "entityEnglishId": "Qualitative research", "entityId": "Qualitative research", "freebaseId": "/m/020gjv", "freebaseTypes": ["/book/book_subject"], "id": 204, "matchedText": "qualitative analysis", "matchingTokens": [720, 721], "relevanceScore": 0.7105, "startingPos": 4199, "wikiLink": "http://en.wikipedia.org/wiki/Qualitative_research", "wikidataId": "Q839486"}}, {"py/object": "textrazor.Entity", "_matched_words": [], "json": {"confidenceScore": 1.944, "endingPos": 2784, "entityEnglishId": "Learning environment", "entityId": "Learning environment", "freebaseId": "", "id": 114, "matchedText": "learning environments", "matchingTokens": [475, 476], "relevanceScore": 0.6265, "startingPos": 2763, "wikiLink": "http://en.wikipedia.org/wiki/Learning_environment", "wikidataId": "Q25313434"}}, {"py/object": "textrazor.Entity", "_matched_words": [], "json": {"confidenceScore": 1.065, "endingPos": 1107, "entityEnglishId": "Teacher", "entityId": "Teacher", "freebaseId": "/m/093fw9", "freebaseTypes": ["/people/profession", "/book/book_subject", "/organization/contact_category", "/fictional_universe/character_occupation", "/people/profession"], "id": 271, "matchedText": "teaching", "matchingTokens": [190], "relevanceScore": 0.6188, "startingPos": 1099, "wikiLink": "http://en.wikipedia.org/wiki/Teacher", "wikidataId": "Q37226"}}, {"py/object": "textrazor.Entity", "_matched_words": [], "json": {"confidenceScore": 1.944, "endingPos": 6023, "entityEnglishId": "Attitude (psychology)", "entityId": "Attitude (psychology)", "freebaseId": "/m/048knw4", "freebaseTypes": ["/media_common/quotation_subject", "/book/book_subject"], "id": 253, "matchedText": "Attitude", "matchingTokens": [1033], "relevanceScore": 0.6141, "startingPos": 6015, "wikiLink": "http://en.wikipedia.org/wiki/Attitude_(psychology)", "wikidataId": "Q622645"}}, {"py/object": "textrazor.Entity", "_matched_words": [], "json": {"confidenceScore": 1.319, "endingPos": 6121, "entityEnglishId": "System", "entityId": "System", "freebaseId": "/m/0bj6r", "freebaseTypes": ["/media_common/quotation_subject"], "id": 8, "matchedText": "system", "matchingTokens": [1058], "relevanceScore": 0.5668, "startingPos": 6115, "wikiLink": "http://en.wikipedia.org/wiki/System", "wikidataId": "Q58778"}}]