[{"py/object": "textrazor.Entity", "_matched_words": [], "json": {"confidenceScore": 15.47, "endingPos": 8315, "entityEnglishId": "Gamification", "entityId": "Gamification", "freebaseId": "/m/0cm8xv9", "freebaseTypes": ["/business/business_location", "/business/employer"], "id": 371, "matchedText": "gamification", "matchingTokens": [1363], "relevanceScore": 0.9605, "startingPos": 8303, "wikiLink": "http://en.wikipedia.org/wiki/Gamification", "wikidataId": "Q1067402"}}, {"py/object": "textrazor.Entity", "_matched_words": [], "json": {"confidenceScore": 1.602, "endingPos": 18102, "entityEnglishId": "Chatbot", "entityId": "Chatbot", "freebaseId": "/m/05n_bhx", "freebaseTypes": ["/computer/software_genre", "/internet/website_category"], "id": 260, "matchedText": "bots", "matchingTokens": [2944], "relevanceScore": 0.8884, "startingPos": 18098, "wikiLink": "http://en.wikipedia.org/wiki/Chatbot", "wikidataId": "Q870780"}}, {"py/object": "textrazor.Entity", "_matched_words": [], "json": {"confidenceScore": 1.849, "endingPos": 13390, "entityEnglishId": "Educational game", "entityId": "Educational game", "freebaseId": "/m/01sjp9", "freebaseTypes": ["/cvg/cvg_genre", "/media_common/media_genre", "/book/book_subject"], "id": 31, "matchedText": "educational game", "matchingTokens": [2162, 2163], "relevanceScore": 0.882, "startingPos": 13374, "wikiLink": "http://en.wikipedia.org/wiki/Educational_game", "wikidataId": "Q1140363"}}, {"py/object": "textrazor.Entity", "_matched_words": [], "json": {"confidenceScore": 0.9971, "endingPos": 6059, "entityEnglishId": "Motivation", "entityId": "Motivation", "freebaseId": "/m/0ndxm1q", "freebaseTypes": ["/media_common/quotation_subject", "/book/book_subject", "/media_common/media_genre", "/media_common/literary_genre"], "id": 243, "matchedText": "motivate", "matchingTokens": [1001], "relevanceScore": 0.7974, "startingPos": 6051, "wikiLink": "http://en.wikipedia.org/wiki/Motivation", "wikidataId": "Q644302"}}, {"py/object": "textrazor.Entity", "_matched_words": [], "json": {"confidenceScore": 4.075, "endingPos": 10642, "entityEnglishId": "Educational technology", "entityId": "Educational technology", "freebaseId": "/m/03c4pp0", "freebaseTypes": ["/education/field_of_study", "/people/profession"], "id": 320, "matchedText": "educational technology", "matchingTokens": [1704, 1705], "relevanceScore": 0.7612, "startingPos": 10620, "wikiLink": "http://en.wikipedia.org/wiki/Educational_technology", "wikidataId": "Q1068473"}}, {"py/object": "textrazor.Entity", "_matched_words": [], "json": {"confidenceScore": 1.033, "endingPos": 16732, "entityEnglishId": "Technology integration", "entityId": "Technology integration", "freebaseId": "/m/07_py0", "id": 357, "matchedText": "technology integration", "matchingTokens": [2710, 2711], "relevanceScore": 0.7604, "startingPos": 16710, "wikiLink": "http://en.wikipedia.org/wiki/Technology_integration", "wikidataId": "Q7692612"}}, {"py/object": "textrazor.Entity", "_matched_words": [], "json": {"confidenceScore": 1.426, "endingPos": 14156, "entityEnglishId": "Inclusion (education)", "entityId": "Inclusion (education)", "freebaseId": "/m/0b_199", "id": 228, "matchedText": "inclusion", "matchingTokens": [2281], "relevanceScore": 0.7417, "startingPos": 14147, "wikiLink": "http://en.wikipedia.org/wiki/Inclusion_(education)", "wikidataId": "Q1055771"}}, {"py/object": "textrazor.Entity", "_matched_words": [], "json": {"confidenceScore": 6.261, "endingPos": 14246, "entityEnglishId": "Curriculum", "entityId": "Curriculum", "freebaseId": "/m/02fk8v", "freebaseTypes": ["/book/book_subject", "/education/field_of_study"], "id": 191, "matchedText": "curricula", "matchingTokens": [2296], "relevanceScore": 0.693, "startingPos": 14237, "wikiLink": "http://en.wikipedia.org/wiki/Curriculum", "wikidataId": "Q207137"}}, {"py/object": "textrazor.Entity", "_matched_words": [], "json": {"confidenceScore": 2.94, "endingPos": 8419, "entityEnglishId": "Analytics", "entityId": "Analytics", "freebaseId": "/m/02gcn9", "freebaseTypes": ["/organization/organization_sector", "/business/competitive_space", "/computer/software_genre", "/internet/website_category", "/book/book_subject", "/business/industry", "/media_common/quotation_subject"], "id": 131, "matchedText": "Analytics", "matchingTokens": [1380], "relevanceScore": 0.692, "startingPos": 8410, "wikiLink": "http://en.wikipedia.org/wiki/Analytics", "wikidataId": "Q485396"}}, {"py/object": "textrazor.Entity", "_matched_words": [], "json": {"confidenceScore": 2.363, "endingPos": 11559, "entityEnglishId": "Project-based learning", "entityId": "Project-based learning", "freebaseId": "/m/05jlmv", "id": 59, "matchedText": "project-based", "matchingTokens": [1852], "relevanceScore": 0.6803, "startingPos": 11546, "wikiLink": "http://en.wikipedia.org/wiki/Project-based_learning", "wikidataId": "Q1753447"}}, {"py/object": "textrazor.Entity", "_matched_words": [], "json": {"confidenceScore": 11.71, "endingPos": 17316, "entityEnglishId": "Virtual reality", "entityId": "Virtual reality", "freebaseId": "/m/07_ny", "freebaseTypes": ["/media_common/media_genre", "/fictional_universe/type_of_fictional_setting", "/education/field_of_study", "/book/book_subject", "/film/film_subject"], "id": 186, "matchedText": "Virtual Reality", "matchingTokens": [2813, 2814], "relevanceScore": 0.6692, "startingPos": 17301, "wikiLink": "http://en.wikipedia.org/wiki/Virtual_reality", "wikidataId": "Q170519"}}, {"py/object": "textrazor.Entity", "_matched_words": [], "json": {"confidenceScore": 5.037, "endingPos": 14180, "entityEnglishId": "Teacher", "entityId": "Teacher", "freebaseId": "/m/093fw9", "freebaseTypes": ["/people/profession", "/book/book_subject", "/organization/contact_category", "/fictional_universe/character_occupation", "/people/profession"], "id": 222, "matchedText": "teachin", "matchingTokens": [2286], "relevanceScore": 0.6443, "startingPos": 14173, "wikiLink": "http://en.wikipedia.org/wiki/Teacher", "wikidataId": "Q37226"}}, {"py/object": "textrazor.Entity", "_matched_words": [], "json": {"confidenceScore": 1.724, "endingPos": 7773, "entityEnglishId": "Goal orientation", "entityId": "Goal orientation", "freebaseId": "/m/0ds7tqq", "id": 283, "matchedText": "Goal orientation", "matchingTokens": [1277, 1278], "relevanceScore": 0.6409, "startingPos": 7757, "wikiLink": "http://en.wikipedia.org/wiki/Goal_orientation", "wikidataId": "Q5575175"}}, {"py/object": "textrazor.Entity", "_matched_words": [], "json": {"confidenceScore": 1.296, "endingPos": 1554, "entityEnglishId": "Design Patterns", "entityId": "Design Patterns", "freebaseId": "/m/0b21p", "freebaseTypes": ["/book/book", "/book/written_work"], "id": 181, "matchedText": "design patterns", "matchingTokens": [262, 263], "relevanceScore": 0.6268, "startingPos": 1539, "type": ["Work", "WrittenWork", "Book"], "wikiLink": "http://en.wikipedia.org/wiki/Design_Patterns", "wikidataId": "Q1283101"}}, {"py/object": "textrazor.Entity", "_matched_words": [], "json": {"confidenceScore": 1.869, "endingPos": 17197, "entityEnglishId": "Immersion (virtual reality)", "entityId": "Immersion (virtual reality)", "freebaseId": "/m/02qfywy", "freebaseTypes": ["/visual_art/visual_art_genre", "/business/product_line"], "id": 395, "matchedText": "Immersion", "matchingTokens": [2790], "relevanceScore": 0.6247, "startingPos": 17188, "wikiLink": "http://en.wikipedia.org/wiki/Immersion_(virtual_reality)", "wikidataId": "Q1660060"}}]