[{"py/object": "textrazor.Entity", "_matched_words": [], "json": {"confidenceScore": 2.116, "endingPos": 1842, "entityEnglishId": "Weight", "entityId": "Weight", "freebaseId": "/m/085x_", "id": 12, "matchedText": "weight", "matchingTokens": [366], "relevanceScore": 0.7809, "startingPos": 1836, "wikiLink": "http://en.wikipedia.org/wiki/Weight", "wikidataId": "Q25288"}}, {"py/object": "textrazor.Entity", "_matched_words": [], "json": {"confidenceScore": 3.786, "endingPos": 3893, "entityEnglishId": "Mobile app", "entityId": "Mobile app", "freebaseId": "/m/0h94y36", "freebaseTypes": ["/business/industry", "/business/competitive_space", "/organization/organization_sector", "/computer/operating_system", "/computer/software_genre", "/cvg/cvg_genre", "/book/book_subject", "/internet/website_category", "/business/consumer_product", "/media_common/media_genre"], "id": 49, "matchedText": "App", "matchingTokens": [779], "relevanceScore": 0.7008, "startingPos": 3890, "wikiLink": "http://en.wikipedia.org/wiki/Mobile_app", "wikidataId": "Q620615"}}, {"py/object": "textrazor.Entity", "_matched_words": [], "json": {"confidenceScore": 3.276, "endingPos": 60, "entityEnglishId": "Educational technology", "entityId": "Educational technology", "freebaseId": "/m/03c4pp0", "freebaseTypes": ["/education/field_of_study", "/people/profession"], "id": 23, "matchedText": "Educational Technology", "matchingTokens": [7, 8], "relevanceScore": 0.663, "startingPos": 38, "wikiLink": "http://en.wikipedia.org/wiki/Educational_technology", "wikidataId": "Q1068473"}}, {"py/object": "textrazor.Entity", "_matched_words": [], "json": {"confidenceScore": 12.7, "endingPos": 2824, "entityEnglishId": "Gravity", "entityId": "Gravity", "freebaseId": "/m/09lw1", "freebaseTypes": ["/book/book_subject", "/physics/fundamental_interaction"], "id": 98, "matchedText": "gravity", "matchingTokens": [564], "relevanceScore": 0.6125, "startingPos": 2817, "wikiLink": "http://en.wikipedia.org/wiki/Gravity", "wikidataId": "Q11412"}}, {"py/object": "textrazor.Entity", "_matched_words": [], "json": {"confidenceScore": 3.284, "endingPos": 2927, "entityEnglishId": "Museum", "entityId": "Museum", "freebaseId": "/m/09cmq", "freebaseTypes": ["/projects/project_focus", "/book/book_subject", "/architecture/building_complex_function", "/architecture/building_function", "/exhibitions/exhibition_subject"], "id": 54, "matchedText": "Museum", "matchingTokens": [585], "relevanceScore": 0.5627, "startingPos": 2921, "wikiLink": "http://en.wikipedia.org/wiki/Museum", "wikidataId": "Q33506"}}, {"py/object": "textrazor.Entity", "_matched_words": [], "json": {"confidenceScore": 5.896, "endingPos": 3528, "entityEnglishId": "Geography", "entityId": "Geography", "freebaseId": "/m/034ns", "freebaseTypes": ["/organization/organization_sector", "/tv/tv_subject", "/media_common/literary_genre", "/media_common/media_genre", "/education/field_of_study", "/award/award_discipline", "/book/book_subject"], "id": 87, "matchedText": "Geographical", "matchingTokens": [702], "relevanceScore": 0.5428, "startingPos": 3516, "wikiLink": "http://en.wikipedia.org/wiki/Geography", "wikidataId": "Q1071"}}, {"py/object": "textrazor.Entity", "_matched_words": [], "json": {"confidenceScore": 1.854, "endingPos": 2006, "entityEnglishId": "Book", "entityId": "Book", "freebaseId": "/m/0bt_c3", "freebaseTypes": ["/media_common/literary_genre", "/media_common/media_genre", "/business/consumer_product", "/visual_art/visual_art_support"], "id": 65, "matchedText": "book", "matchingTokens": [400], "relevanceScore": 0.5221, "startingPos": 2002, "wikiLink": "http://en.wikipedia.org/wiki/Book", "wikidataId": "Q571"}}, {"py/object": "textrazor.Entity", "_matched_words": [], "json": {"confidenceScore": 4.85, "endingPos": 3015, "entityEnglishId": "Space", "entityId": "Space", "freebaseId": "/m/06wqb", "freebaseTypes": ["/book/book_subject", "/media_common/quotation_subject"], "id": 90, "matchedText": "space", "matchingTokens": [603], "relevanceScore": 0.5105, "startingPos": 3010, "wikiLink": "http://en.wikipedia.org/wiki/Space", "wikidataId": "Q107"}}, {"py/object": "textrazor.Entity", "_matched_words": [], "json": {"confidenceScore": 16.86, "endingPos": 3115, "entityEnglishId": "Earth", "entityId": "Earth", "freebaseId": "/m/02j71", "freebaseTypes": ["/visual_art/art_subject", "/astronomy/celestial_object", "/organization/contact_category", "/astronomy/planet", "/fictional_universe/fictional_setting", "/book/book_subject", "/astronomy/star_system_body", "/organization/organization_scope", "/astronomy/orbital_relationship", "/astronomy/celestial_object_with_coordinate_system", "/location/statistical_region", "/location/location", "/media_common/quotation_subject", "/tv/tv_subject"], "id": 77, "matchedText": "world", "matchingTokens": [622], "relevanceScore": 0.5104, "startingPos": 3110, "type": ["CelestialBody", "Planet"], "wikiLink": "http://en.wikipedia.org/wiki/Earth", "wikidataId": "Q2"}}, {"py/object": "textrazor.Entity", "_matched_words": [], "json": {"confidenceScore": 1.421, "endingPos": 2880, "entityEnglishId": "Education", "entityId": "Education", "freebaseId": "/m/02jfc", "freebaseTypes": ["/business/customer", "/film/film_genre", "/games/game_genre", "/tv/tv_genre", "/organization/organization_sector", "/architecture/building_complex_function", "/media_common/media_genre", "/book/book_subject", "/people/professional_field", "/government/government_service", "/media_common/quotation_subject", "/organization/contact_category", "/book/periodical_subject", "/business/competitive_space", "/cvg/cvg_genre", "/business/brand", "/conferences/conference_subject", "/media_common/literary_genre", "/broadcast/genre", "/award/award_discipline", "/internet/website_category", "/education/field_of_study", "/atom/feed_category", "/business/industry", "/organization/organization_type", "/film/film_subject"], "id": 40, "matchedText": "Educational", "matchingTokens": [575], "relevanceScore": 0.5052, "startingPos": 2869, "wikiLink": "http://en.wikipedia.org/wiki/Education", "wikidataId": "Q8434"}}, {"py/object": "textrazor.Entity", "_matched_words": [], "json": {"confidenceScore": 1.952, "endingPos": 2051, "entityEnglishId": "Textbook", "entityId": "Textbook", "freebaseId": "/m/01lph_", "freebaseTypes": ["/media_common/literary_genre", "/media_common/media_genre", "/award/award_discipline"], "id": 9, "matchedText": "text books", "matchingTokens": [410, 411], "relevanceScore": 0.4798, "startingPos": 2041, "wikiLink": "http://en.wikipedia.org/wiki/Textbook", "wikidataId": "Q83790"}}, {"py/object": "textrazor.Entity", "_matched_words": [], "json": {"confidenceScore": 19.11, "endingPos": 2730, "entityEnglishId": "Physics", "entityId": "Physics", "freebaseId": "/m/05qjt", "freebaseTypes": ["/book/book_subject", "/media_common/media_genre", "/education/field_of_study", "/exhibitions/exhibition_subject", "/event/speech_topic", "/media_common/quotation_subject", "/atom/feed_category", "/award/award_discipline", "/organization/organization_sector", "/broadcast/genre", "/media_common/literary_genre", "/people/professional_field", "/education/educational_degree"], "id": 62, "matchedText": "Physics", "matchingTokens": [547], "relevanceScore": 0.4713, "startingPos": 2723, "wikiLink": "http://en.wikipedia.org/wiki/Physics", "wikidataId": "Q413"}}, {"py/object": "textrazor.Entity", "_matched_words": [], "json": {"confidenceScore": 4.956, "endingPos": 2214, "entityEnglishId": "Library", "entityId": "Library", "freebaseId": "/m/04h8h", "freebaseTypes": ["/location/location", "/internet/website_category", "/book/book_subject", "/architecture/building_function", "/business/industry", "/organization/organization_sector", "/computer/software_genre", "/media_common/quotation_subject", "/organization/contact_category"], "id": 55, "matchedText": "library", "matchingTokens": [444], "relevanceScore": 0.4486, "startingPos": 2207, "wikiLink": "http://en.wikipedia.org/wiki/Library", "wikidataId": "Q7075"}}, {"py/object": "textrazor.Entity", "_matched_words": [], "json": {"confidenceScore": 5.477, "endingPos": 1496, "entityEnglishId": "Amazon Kindle", "entityId": "Amazon Kindle", "freebaseId": "/m/03d068f", "freebaseTypes": ["/business/consumer_product", "/award/ranked_item", "/business/brand", "/book/book_edition", "/business/product_line", "/media_common/cataloged_instance"], "id": 59, "matchedText": "Kindle", "matchingTokens": [298], "relevanceScore": 0.4371, "startingPos": 1490, "type": ["Device", "InformationAppliance"], "wikiLink": "http://en.wikipedia.org/wiki/Amazon_Kindle", "wikidataId": "Q136469"}}, {"py/object": "textrazor.Entity", "_matched_words": [], "json": {"confidenceScore": 15.39, "endingPos": 304, "entityEnglishId": "Science", "entityId": "Science", "freebaseId": "/m/06mq7", "freebaseTypes": ["/award/award_discipline", "/radio/radio_subject", "/book/periodical_subject", "/media_common/quotation_subject", "/internet/website_category", "/education/field_of_study", "/theater/theater_genre", "/organization/organization_sector", "/book/book_subject", "/media_common/literary_genre", "/film/film_genre", "/media_common/netflix_genre", "/film/film_subject", "/broadcast/genre", "/tv/tv_subject", "/tv/tv_genre", "/media_common/media_genre"], "id": 14, "matchedText": "Science", "matchingTokens": [55], "relevanceScore": 0.4331, "startingPos": 297, "wikiLink": "http://en.wikipedia.org/wiki/Science", "wikidataId": "Q336"}}]